odoo/addons/product_vendor_code_search/README.rst
odoo/addons/product_vendor_code_search/__init__.py
odoo/addons/product_vendor_code_search/__manifest__.py
odoo/addons/product_vendor_code_search/i18n/ca_ES.po
odoo/addons/product_vendor_code_search/i18n/es.po
odoo/addons/product_vendor_code_search/models/__init__.py
odoo/addons/product_vendor_code_search/models/product_product.py
odoo/addons/product_vendor_code_search/models/product_template.py
odoo/addons/product_vendor_code_search/readme/CONTRIBUTORS.md
odoo/addons/product_vendor_code_search/readme/DESCRIPTION.md
odoo/addons/product_vendor_code_search/readme/USAGE.md
odoo/addons/product_vendor_code_search/static/description/icon.png
odoo/addons/product_vendor_code_search/static/description/index.html
odoo/addons/product_vendor_code_search/tests/__init__.py
odoo/addons/product_vendor_code_search/tests/test_product_vendor_code_search.py
odoo/addons/product_vendor_code_search/views/product_views.xml
odoo_addon_product_vendor_code_search-16.0.1.0.0.1.dist-info/METADATA
odoo_addon_product_vendor_code_search-16.0.1.0.0.1.dist-info/WHEEL
odoo_addon_product_vendor_code_search-16.0.1.0.0.1.dist-info/top_level.txt
odoo_addon_product_vendor_code_search-16.0.1.0.0.1.dist-info/RECORD
